bkmk/__init__.py
bkmk/__main__.py
bkmk/base.py
bkmk/bkmk_json.py
bkmk/chrome_json.py
bkmk/netscape_html.py
bkmk/xbel.py
bkmk-0.1.dist-info/licenses/LICENSE
bkmk-0.1.dist-info/METADATA
bkmk-0.1.dist-info/WHEEL
bkmk-0.1.dist-info/entry_points.txt
bkmk-0.1.dist-info/top_level.txt
bkmk-0.1.dist-info/RECORD
