Metadata-Version: 2.4
Name: bkmk
Version: 0.1
Summary: Universal bookmark file format utility
Author-email: Ximin Luo <infinity0@pwned.gg>
Project-URL: Homepage, https://github.com/infinity0/bkmk
Project-URL: Bug Tracker, https://github.com/infinity0/bkmk/issues
Classifier: Programming Language :: Python :: 3
Classifier: License :: OSI Approved :: MIT License
Classifier: Operating System :: OS Independent
Requires-Python: >=3.9
License-File: LICENSE
Dynamic: license-file
